tree_sitter_move/__init__.py
tree_sitter_move/__init__.pyi
tree_sitter_move/_binding.abi3.so
tree_sitter_move/binding.c
tree_sitter_move/py.typed
tree_sitter_move-0.0.1.dist-info/licenses/LICENSE
tree_sitter_move-0.0.1.dist-info/METADATA
tree_sitter_move-0.0.1.dist-info/WHEEL
tree_sitter_move-0.0.1.dist-info/top_level.txt
tree_sitter_move-0.0.1.dist-info/RECORD
