Metadata-Version: 2.4
Name: tree-sitter-move
Version: 0.0.1
Summary: Move grammar for tree-sitter
Author: Tree-sitter Move Contributors
License: Copyright © Aptos Foundation
Project-URL: Homepage, https://github.com/tree-sitter/tree-sitter-move
Project-URL: Repository, https://github.com/tree-sitter/tree-sitter-move
Project-URL: Issues, https://github.com/tree-sitter/tree-sitter-move/issues
Keywords: incremental,parsing,tree-sitter,move,blockchain,aptos
Classifier: Development Status :: 4 - Beta
Classifier: Intended Audience :: Developers
Classifier: License :: OSI Approved :: Apache Software License
Classifier: Programming Language :: Python :: 3
Classifier: Programming Language :: Python :: 3.8
Classifier: Programming Language :: Python :: 3.9
Classifier: Programming Language :: Python :: 3.10
Classifier: Programming Language :: Python :: 3.11
Classifier: Programming Language :: Python :: 3.12
Classifier: Topic :: Software Development :: Compilers
Classifier: Topic :: Software Development :: Libraries :: Python Modules
Classifier: Topic :: Text Processing :: Linguistic
Classifier: Typing :: Typed
Requires-Python: >=3.8
License-File: LICENSE
Requires-Dist: tree-sitter>=0.21.0
Provides-Extra: dev
Requires-Dist: pytest>=6.0; extra == "dev"
Requires-Dist: build>=0.8.0; extra == "dev"
Requires-Dist: twine>=4.0.0; extra == "dev"
Dynamic: license-file
